README.md
setup.cfg
setup.py
ccmf/__init__.py
ccmf.egg-info/PKG-INFO
ccmf.egg-info/SOURCES.txt
ccmf.egg-info/dependency_links.txt
ccmf.egg-info/requires.txt
ccmf.egg-info/top_level.txt
ccmf/ccmf/__init__.py
ccmf/ccmf/ccmf.py
ccmf/circuit/__init__.py
ccmf/circuit/circuit.py
ccmf/circuit/sign.py
ccmf/dataset/__init__.py
ccmf/dataset/datasets.py
ccmf/dataset/generate.py
ccmf/gui/__init__.py
ccmf/gui/tk/__init__.py
ccmf/gui/tk/circuit_editor.py
ccmf/gui/tk/gui_circuit/__init__.py
ccmf/gui/tk/gui_circuit/gui_circuit.py
ccmf/gui/tk/gui_circuit/gui_element.py
ccmf/gui/tk/gui_circuit/link.py
ccmf/gui/tk/gui_circuit/node.py
ccmf/inference/__init__.py
ccmf/inference/inference.py
ccmf/inference/map.py
ccmf/inference/mcmc.py
ccmf/model/__init__.py
ccmf/model/base/__init__.py
ccmf/model/base/model.py
ccmf/model/linear/__init__.py
ccmf/model/linear/base.py
ccmf/model/linear/uniform.py