Metadata-Version: 1.2
Name: ccmf
Version: 0.0.1
Summary: Circuit-constrained matrix factorization
Home-page: https://github.com/kclamar/ccmf
Author: Ka Chung Lam
Author-email: kclamar@connect.ust.hk
License: MIT license
Download-URL: https://github.com/kclamar/ccmf/archive/v0.0.1.tar.gz
Platform: UNKNOWN
Classifier: Development Status :: 3 - Alpha
Classifier: Intended Audience :: Developers
Classifier: Topic :: Software Development :: Build Tools
Classifier: License :: OSI Approved :: MIT License
Classifier: Programming Language :: Python :: 3
Classifier: Programming Language :: Python :: 3.4
Classifier: Programming Language :: Python :: 3.5
Classifier: Programming Language :: Python :: 3.6
Requires-Python: >=3.5
